torch_inception_resnet_v2/__init__.py
torch_inception_resnet_v2/model.py
torch_inception_resnet_v2/blocks/__init__.py
torch_inception_resnet_v2/blocks/inception/__init__.py
torch_inception_resnet_v2/blocks/inception/a.py
torch_inception_resnet_v2/blocks/inception/b.py
torch_inception_resnet_v2/blocks/inception/c.py
torch_inception_resnet_v2/blocks/inception/inception_resnet.py
torch_inception_resnet_v2/blocks/reduction/__init__.py
torch_inception_resnet_v2/blocks/reduction/a.py
torch_inception_resnet_v2/blocks/reduction/b.py
torch_inception_resnet_v2/blocks/reduction/reduction_block.py
torch_inception_resnet_v2/blocks/stem/__init__.py
torch_inception_resnet_v2/blocks/stem/stem.py
torch_inception_resnet_v2/hparams/__init__.py
torch_inception_resnet_v2/hparams/params.py
torch_inception_resnet_v2/utils/__init__.py
torch_inception_resnet_v2/utils/branch.py
torch_inception_resnet_v2/utils/concurrent.py
torch_inception_resnet_v2/utils/convolution_config.py
torch_inception_resnet_v2/utils/functions.py
torch_inception_resnet_v2/utils/repeated.py
torch_inception_resnet_v2-0.0.33.dist-info/LICENSE
torch_inception_resnet_v2-0.0.33.dist-info/METADATA
torch_inception_resnet_v2-0.0.33.dist-info/WHEEL
torch_inception_resnet_v2-0.0.33.dist-info/top_level.txt
torch_inception_resnet_v2-0.0.33.dist-info/RECORD
